LICENSE.txt
README.md
setup.py
textmining_module/__init__.py
textmining_module/extractor.py
textmining_module/miner.py
textmining_module.egg-info/PKG-INFO
textmining_module.egg-info/SOURCES.txt
textmining_module.egg-info/dependency_links.txt
textmining_module.egg-info/requires.txt
textmining_module.egg-info/top_level.txt