Metadata-Version: 2.1
Name: textmining_module
Version: 0.1.4
Summary: A Python Module for Comprehensive Text Mining, including Keyword Extraction and Text Analysis.
Home-page: https://github.com/knowusuboaky/textmining_module
Author: Kwadwo Daddy Nyame Owusu - Boakye
Author-email: kwadwo.owusuboakye@outlook.com
Keywords: text mining,clustering,correlation,similarity,keyword extraction,text analysis,scoring,bining,data processing,Python
Classifier: Development Status :: 3 - Alpha
Classifier: Intended Audience :: Developers
Classifier: Topic :: Software Development :: Build Tools
Classifier: License :: OSI Approved :: MIT License
Classifier: Programming Language :: Python :: 3
Classifier: Programming Language :: Python :: 3.6
Classifier: Programming Language :: Python :: 3.7
Classifier: Programming Language :: Python :: 3.8
Classifier: Programming Language :: Python :: 3.9
Classifier: Programming Language :: Python :: 3.10
Classifier: Programming Language :: Python :: 3.11
Classifier: Programming Language :: Python :: 3.12
Requires-Python: >=3.6
License-File: LICENSE.txt
Requires-Dist: pandas>=1.1.5
Requires-Dist: numpy>=1.19.5
Requires-Dist: scikit-learn>=0.24.1
Requires-Dist: imbalanced-learn>=0.7.0
Requires-Dist: mlxtend>=0.18.0
Requires-Dist: yake
Requires-Dist: matplotlib>=3.3.3
Requires-Dist: seaborn>=0.11.1
Requires-Dist: scipy>=1.5.4
Requires-Dist: ipywidgets>=7.6.3
Requires-Dist: IPython>=7.22.0
Requires-Dist: pandas>=1.0.0
Requires-Dist: nltk>=3.5
Requires-Dist: spacy>=2.3.2
Requires-Dist: scikit-learn>=0.23.1
